{
    "version": {
        "date": "2025-06-08 18:18:57",
        "plugin": "infohub_welcome",
        "data_checksum": "a5446a9e8eb740fc22989a8fdb4fe22b",
        "language": "tr",
        "language_name": "Turkish",
        "language_name_local": "Türk Türkçesi",
        "country": "",
        "country_name": "",
        "file_type": "translate_file",
        "has_manual_translations": "false"
    },
    "launcher": {
        "title": "Hoşgeldiniz Welcome Welcome Hoşgeldiniz",
        "description": "InfoHub'a hoş geldiniz. Bu, InfoHub'un yapabileceği bir ilham yolculuğudur ve gelecekte yapılacak."
    },
    "data": {
        "infohub_welcome_menu": {
            "WELCOME_KEY": "Hoşgeldiniz Welcome Welcome Hoşgeldiniz",
            "YOU_CAN_DO_ALL_THIS_KEY": "Tüm bunları yapabilirsiniz",
            "IF_YOU_LIKE_TECH_KEY": "Teknolojiyi seviyorsanız"
        },
        "infohub_welcome_tech": {
            "INFOHUB_KEY": "Infohub",
            "THIS_IS_NOT_ABOUT_SHARING._INFOHUB_IS_ABOUT_YOUR_PRIVATE_DATA,_ENCRYPTED_ON_YOUR_OWN_TRUSTED_SERVER._KEY": "Bu paylaşım hakkında değil. Infohub özel verileriniz hakkında, kendi güvenilir sunucunuzda şifrelenir.",
            "YOUR_OWN_PLACE_ON_THE_INTERNET_THAT_YOU_CAN_ACCESS_WHENEVER_YOU_WANT_TO._KEY": "İnternetteki kendi yeriniz, istediğiniz zaman erişebilirsiniz.",
            "QUICK_FACTS_KEY": "Hızlı gerçekler",
            "INFOHUB_IS_GPL3_LICENSED_KEY": "Infohub gpl3 lisanslı",
            "FULL_DOCUMENTATION_AT_KEY": "Tam belgeleri",
            "PLUGINS_WORK_AND_LOOK_THE_SAME_ON_BOTH_CLIENT_AND_SERVER_KEY": "Plugins çalışır ve hem müşteri hem de sunucuda aynı görünür",
            "MESSAGES_FLOW_IN_THE_SYSTEM_KEY": "Sistemdeki mesaj akışı",
            "SUB-CALL_TO_ANY_PLUGIN_ON_ANY_NODE_KEY": "Sub-call to any plugin on any node",
            "PLUGINS_AUTOSTART_WHEN_NEEDED_KEY": "Gerektiğinde Plugins otostart",
            "CLIENT_RENDERERS_MANAGE_THE_HTML_KEY": "Müşteriler html'ı yönetiyor",
            "CLIENT_NEVER_REFRESH_THE_PAGE_KEY": "Müşteri sayfayı asla yenilemedi",
            "CLIENT_USE_LOCAL_STORAGE_FOR_OFFLINE_USE_KEY": "Müşteri çevrimdışı kullanım için yerel depolama kullanır",
            "LOGGING_TO_FILE_AND_CONSOLE_KEY": "Dosyaya ve konsola gitmek",
            "PLUGINS_IN_PHP_AND_JAVASCRIPT_KEY": "Php ve javascript",
            "STRONGLY_TYPED_(YES_YOU_READ_RIGHT)_KEY": "Güçlü bir şekilde tiplenmiş (sağ okuduğunuzda)",
            "AUTOMATIC_TESTS_WRITE_THEMSELF_(YES_YOU_READ_RIGHT)_KEY": "Otomatik testler onları kendiniz yazar (doğru okudunuz)",
            "QUICK_KICK_OUT_TESTS_AT_THE_DOOR_KEY": "Hızlı testleri kapıda açın",
            "DOMAINS_CAN_GET_DIFFERENT_CONTENTS_KEY": "Domainler farklı içerik alabilir",
            "DID_I_MENTION_FULLY_RESPONSIVE?_KEY": "Tamamen duyarlı mı yazdım?",
            "THE_GENERIC_WEB_PLATFORM_KEY": "Jenerik web platformu",
            "A_PLATFORM_TAKE_CARE_OF_ALL_THE_STUFF_THAT_YOU_KNOW_YOU_NEED_BUT_WOULD_TAKE_AGES_TO_WRITE._KEY": "Bir platform ihtiyacınız olan tüm şeyleri önemsiyor, ancak yazmak için yaş alır.",
            "THERE_ARE_MANY_POPULAR_PLATFORMS,_HERE_ARE_A_FEW_POPULAR_ONES:_KEY": "Birçok popüler platform var, burada birkaç popüler var:",
            "THEY_ARE_TARGETING_DIFFERENT_AREAS_AND_CAN_BE_EXPANDED_WITH_MODULES._KEY": "Farklı alanları hedef alıyorlar ve modüllerle genişletilebilirler.",
            "INFOHUB_IS_A_GENERIC_PLATFORM._IT_DOES_NOTHING_UNTIL_IT_GETS_SOME_PLUGINS_THAT_TELL_IT_WHAT_TO_DO._KEY": "Infohub genel bir platformdur. Ne yapacağını söyleyen bazı eklentilere kadar hiçbir şey yapmaz.",
            "THERE_ARE_SOME_DEMO_PLUGINS_INCLUDED_KEY": "Dahil bazı demo eklentileri var",
            "GETTING_STARTED_KEY": "Başlanmaya başladı",
            "GPL_3_LICENSED._KEY": "Gpl 3 lisanslı.",
            "NO_COSTS_FOR_YOU_TO_GET_STARTED._KEY": "Başlamanız için hiçbir masraf yok.",
            "JUST_DOWNLOAD_AND_INSTALL._KEY": "Sadece indirme ve yükleme.",
            "INFOHUB_INSTALLATION_IS_SIMPLE,_COPY_VERY_FEW_FILES,_AND_YOU_ARE_ON._KEY": "Infohub kurulumu basittir, çok az dosyayı kopyalayın ve üzerindesiniz.",
            "WORKBENCH_KEY": "Workbench",
            "WITH_THE_OPTIONAL_WORKBENCH_YOU_CAN_START_PLUGINS_AND_SE_THE_GRAPHICAL_USER_INTERFACE._KEY": "Seçmeli çalışmabench ile eklentilere başlayabilir ve grafik kullanıcı arayüzünü ayırt edebilirsiniz.",
            "THIS_TURNS_INFOHUB_INTO_A_WEB_OPERATING_SYSTEM._KEY": "Bu, infohub'u bir web işletim sistemine dönüştürür.",
            "YOU_CAN_WRITE_PLUGINS_KEY": "Eklentileri yazabilirsiniz",
            "PLUGINS_ARE_SIMPLE_TO_CREATE,_COPY_THE_INFOHUB_PLUGIN_TEMPLATE_TO_A_NEW_NAME_AND_START_CODING._KEY": "Plugins oluşturmak için basittir, Infohub eklentisini yeni bir isime kopyalayın ve kodlamaya başlayın.",
            "YOU_CAN_WRITE_JAVASCRIPT_PLUGINS_FOR_THE_CLIENT_AND_PHP_PLUGINS_FOR_THE_SERVER._KEY": "Sunucu için javascript eklentilerini ve php'leri yazabilirsiniz.",
            "THE_WAY_YOU_DO_IT_IS_IDENTICAL_AND_WORKS_IDENTICAL._KEY": "Bunu yapmanın yolu aynıdır ve aynı şekilde çalışır.",
            "LEAD_WORDS_IN_BUILDING_INFOHUB_KEY": "Infohub inşasındaki kelimeler",
            "NO_EXCEPTIONS_KEY": "Hiçbir istisna istisna yok",
            "THAT_MEANS_ALL_DATA_ARE_STORED_IN_STORAGE._KEY": "Bu, tüm verilerin depolamada depolanması anlamına gelir.",
            "ALL_TRAFFIC_ARE_REDIRECTED_WITH_EXCHANGE._KEY": "Tüm trafik değişim ile yönlendirilir.",
            "EVERYONE_HAVE_TO_LOGIN_TO_ACCESS_DATA._KEY": "Herkes verilere erişmek için giriş yapmak zorunda.",
            "MAKE_IT_SIMPLE_KEY": "Basit yapın",
            "SIMPLE_MEANS_TO_WRITE_CODE_THAT_EVERYONE_CAN_READ._KEY": "Basit, herkesin okuyabileceği kod yazmak anlamına gelir.",
            "SIMPLE_CODE_OFTEN_MEAN_FAST_CODE._KEY": "Basit kod genellikle hızlı kod anlamına gelir.",
            "CHOOSE_SIMPLE_OVER_FAST_BUT_AVOID_SLOW_CODE._KEY": "Hızlı basit seçin ama yavaş koddan kaçının.",
            "CHOOSE_SOLUTIONS_THAT_ARE_SIMPLE_TO_UNDERSTAND_AND_SIMPLE_TO_IMPLEMENT._KEY": "Uygulanacak basit ve basit olan çözümleri seçin.",
            "LET_INFOHUB_STAY_SMALL,_SIMPLE_AND_FAST._KEY": "Infohub küçük, basit ve hızlı kalalım.",
            "PUT_NEW_ABILITIES_IN_PLUGINS._KEY": "Eklentilerde yeni yetenekleri koyun.",
            "SELF_CONTAINING_KEY": "Kendini içeren",
            "PLUGIN_HAVE_NO_DEPENDENCIES_ON_OTHER_PLUGINS._KEY": "Plugin'in diğer eklentilere bağımlısı yoktur.",
            "PLUGIN_CAN_BE_USED_IN_OTHER_PROJECTS_WITH_NO_CHANGES._KEY": "Plugin başka projelerde değişiklikler olmadan kullanılabilir.",
            "INDEPENDENT_PLUGINS_KEY": "Bağımsız eklentiler",
            "EACH_PLUGIN_IS_JUST_ONE_FILE,_ONE_CLASS,_AND_THEY_ALL_EXTEND_THE_BASE_CLASS._KEY": "Her eklenti sadece bir dosya, bir sınıf ve hepsi temel sınıfı genişletir.",
            "EACH_PLUGIN_CAN_BE_USED_INDEPENDENTLY_IN_ANOTHER_ENVIRONMENT_IF_YOU_LIKE._KEY": "Her eklenti, isterseniz başka bir ortamda bağımsız olarak kullanılabilir.",
            "GIVE_AN_ARRAY_TO_THE_PLUGIN,_THE_PLUGIN_HANDLE_THE_ARRAY_AND_GIVE_YOU_AN_ARRAY_WITH_THE_ANSWER._KEY": "Eklentiye bir dizi verin, eklentiyi ele alalım ve cevapla bir dizi verin.",
            "MESSAGE_FLOW_KEY": "Mesaj akışı",
            "INFOHUB_EXCHANGE_TAKE_CARE_OF_THE_MESSAGES_BETWEEN_THE_PLUGINS._KEY": "Infohub exchange, eklentiler arasındaki mesajları önemsiyor.",
            "MESSAGES_ARE_SENT_BETWEEN_THE_CLIENT_AND_SERVER_WITHOUT_ANY_EFFORT._KEY": "Mesajlar, herhangi bir çaba olmadan müşteri ve sunucu arasında gönderilir.",
            "YOU_CAN_DO_A_SUB_CALL_FROM_AND_TO_ANY_NODE._NODES_ARE_THE_CLIENT,_THE_SERVER_AND_OTHER_INFOHUB_SERVERS_THAT_GOT_NODE_NAMES._KEY": "Bir alt çağrıyı ve herhangi bir düğüme yapabilirsiniz. Nodes müşteri, sunucu ve diğer Infohub sunucularıdır.",
            "EACH_MESSAGE_CONTAIN_ITS_OWN_CALL_STACK_AND_CAN_FIND_ITS_OWN_WAY_BACK_TO_THE_CALLER._KEY": "Her mesaj kendi çağrı yığını içeriyor ve aramacıya kendi yolunu bulabilir.",
            "AUTOMATIC_PLUGIN_START_KEY": "Otomatik eklenti başlangıç başlar",
            "IF_A_MESSAGE_GOES_TO_A_PLUGIN_THAT_IS_NOT_STARTED_THEN_IT_IS_PUT_ASIDE_AND_THE_PLUGIN_IS_REQUESTED._KEY": "Bir mesaj başlamadığı bir eklentiye giderse, o zaman geri alınır ve eklenti talep edilir.",
            "WHEN_THE_PLUGIN_HAVE_STARTED_THEN_THE_MESSAGES_TO_THAT_PLUGIN_COME_BACK_IN_THE_FLOW._KEY": "Eklenti başladığında, o eklentiye mesajlar akışta geri döndü.",
            "WEB_WORKERS_KEY": "Web işçileri",
            "(UNDER_DEVELOPMENT)_IN_THE_BROWSER_YOUR_PLUGINS_RUN_AS_WEB_WORKERS_TO_MAKE_SURE_THEY_ARE_ENCAPSULATED_AND_RESTRICTED_FROM_MUCH_OF_THE_BROWSER_FEATURES._KEY": "(geliştirme) tarayıcınızda eklentiler web işçileri olarak çalıştırılır ve tarayıcı özelliklerinin çoğundan kısıtlanır ve sınırlandırılır.",
            "LOGGING_KEY": "Logging",
            "YOU_CAN_ENABLE_LOGGING_IN_THE_GENERAL_CONFIGURATION,_THEN_THE_SERVER_LOGS_TO_FILES_AND_THE_CLIENT_LOGS_TO_THE_CONSOLE._KEY": "Genel yapılandırmada oturum açabilirsiniz, sonra sunucu dosyalarına ve müşteri girişlerine konsola girer.",
            "THE_CONSOLE_MESSAGES_ARE_A_GREAT_SOURCE_FOR_FINDING_ERRORS._KEY": "Konsol mesajları hataları bulmak için harika bir kaynaktır.",
            "YOU_DO_NOT_HAVE_TO_ADD_ANY_LOGGING_COMMANDS_TO_YOUR_CODE._KEY": "Kodunuza herhangi bir giriş komut eklemek zorunda değilsiniz.",
            "THAT_IS_TAKEN_CARE_OF_BY_THE_CALLER_FUNCTIONS_CMD()_AND_INTERNAL_CMD()._KEY": "Bu, caller işlevleri cmd() ve internal cmd() tarafından dikkate alınır.",
            "CALLER_FUNCTIONS_KEY": "Caller işlevleri",
            "EACH_PLUGIN_HAVE_ONLY_ONE_PUBLIC_FUNCTION:_CMD()._KEY": "Her eklenti sadece bir kamu işlevi vardır: cmd().",
            "THE_MESSAGE_GOES_INTO_THAT_FUNCTION_AND_IT_CALLS_THE_RIGHT_CMD_FUNCTION._KEY": "Mesaj bu işlevine gider ve doğru cmd işlevini çağırır.",
            "YOU_WILL_GET_AN_ARRAY_BACK_FROM_CMD_WITH_THE_ANSWER._KEY": "Cevapla cmd'den bir dizi geri alacaksınız.",
            "THE_CMD_FUNCTION_TAKE_CARE_OF_LOGGING,_ERROR_HANDLING,_MEASURE_EXECUTION_TIME,_CHECK_THE_INCOMING_VARIABLES_IN_THE_ARRAY,_RETURNS_A_RETURN-MESSAGE_OR_A_SUB-CALL-MESSAGE._KEY": "Cmd fonksiyonu, oturum açma, hata işleme, yürütme zamanını kontrol edin, serideki gelen değişkenleri kontrol edin, geri dönüşü geri döndürür veya sub-call-message döndürür.",
            "INFOHUB_INNER_WORKINGS_KEY": "Infohub içişler",
            "EVERY_BOX_IS_A_PLUGIN._INFOHUB_STORAGE_USE_PLUGINS_THAT_SPECIALISE_ON_EACH_DATABASE_TYPE._KEY": "Her kutu bir eklentidir. Infohub depolama, her veritabanı türünde uzmanlaşmış eklentileri kullanır.",
            "INFOHUB_RENDER_GET_HTML_FROM_THE_RENDERERS_AND_SEND_TO_INFOHUB_VIEW._ALL_IS_JUST_PLUGINS_AND_YOU_CAN_WRITE_YOUR_OWN_TOO._KEY": "Infohub form, html'yi sunuculardan alır ve infohub görünümüne gönderin. Hepsi sadece eklentiler ve kendinizi de yazabilirsiniz.",
            "SUB-CALL_OR_RETURN_MESSAGE_KEY": "Sub-call or return message",
            "A_PLUGIN_ALWAYS_RETURN_A_VALID_MESSAGE_THAT_CAN_BE_RELEASED_TO_THE_FLOW._KEY": "Bir eklenti her zaman akışa salıverilebilecek geçerli bir mesaj döndürür.",
            "THE_MESSAGE_IS_EITHER_A_RETURN_MESSAGE,_OR_A_SUB-CALL_MESSAGE._KEY": "Mesaj ya bir iade mesajı ya da alt çağrı mesajıdır.",
            "YOU_CAN_DO_A_SUB_CALL_IN_YOUR_FUNCTION_TO_ANYWHERE_AND_THEN_EXPECT_THE_VERY_SAME_FUNCTION_TO_GET_A_RETURN_MESSAGE_WITH_DATA._KEY": "Bir alt çağrıyı her yere yapabilirsiniz ve sonra verilerle geri dönüş mesajı almak için aynı işlevi bekleyebilirsiniz.",
            "YOU_CAN_ATTACH_VARIABLES_IN_THE_SUB_CALL_THAT_WILL_RETURN_UNTOUCHED._SEE_THE_DEMOS_FOR_A_”STEP”_VARIABLE._KEY": "Alt çağrıda değişkenleri ekleyebilirsiniz, böylece geri dönecektir. Bir \"taraf\" değişkeni için demoları görün.",
            "STRONGLY_TYPED_KEY": "Güçlü bir şekilde tiplenmiş",
            "PHP_AND_JAVASCRIPT_CAN_DO_TYPE_JUGGLING_WITHOUT_SAYING_A_PIP._THAT_IS_GREAT._KEY": "Php ve javascript bir pip söylemeden tip juggling yapabilir. Bu harika.",
            "A_GREAT_SOURCE_OF_AGONY_WHEN_YOU_CAN_NOT_FIND_WHERE_IT_HAVE_TYPE_CASTED_AND_DESTROYED_YOUR_DATA._KEY": "Verilerinizi nerede toplandığını ve yok ettiğini bulamazsanız çok daha önce bir kaynak.",
            "EACH_FUNCTION_IN_EVERY_PLUGIN_START_BY_SETTING_DEFAULT_VALUES._KEY": "Her eklentideki her işlev varsayılan değerleri belirleyerek başlar.",
            "NOW_YOU_KNOW_THAT_THE_INCOMING_ARRAY_CONTAIN_WHAT_YOU_EXPECT_AND_NOTHING_MORE._KEY": "Şimdi, gelen dizinin beklediğiniz şeyi ve daha fazla şey olmadığını biliyorsunuz.",
            "WHAT_ABOUT_HTML?_KEY": "Html hakkında ne?",
            "THE_PLUGIN_INFOHUB_VIEW_TAKE_CARE_OF_THE_CONTENT_BOXES_ON_THE_SCREEN._KEY": "Eklenti infohub görünümü ekranda içerik kutularının bakımı alır.",
            "YOU_CAN_SAY_THINGS_LIKE:_INSERT_THIS_HTML_IN_THE_LEFT_BOX,_IN_THE_MIDDLE_OF_THE_OTHER_BOXES._KEY": "Şeyleri şöyle söyleyebilirsiniz: Bu html'yi sol kutuda, diğer kutuların ortasında.",
            "THEN_YOUR_BOX_WILL_BE_INSERTED_THERE_WITH_YOUR_HTML._THERE_ARE_PLUGINS_THAT_HANDLE_HTML,_THE_RENDERERS._KEY": "Sonra kutunuz oraya html ile eklenecek. html'yi yöneten eklentiler var, taşıyıcılar.",
            "NORMAL_PLUGINS,_YOU_GIVE_THEM_AN_ARRAY_AND_GET_AN_ARRAY_BACK_WITH_THE_HTML_KEY": "Normal eklentiler, onlara bir dizi veriyorsunuz ve html ile bir dizi geri alırsınız",
            "RENDERERS_KEY": "Renderers",
            "READY_TO_USE_RENDERERS_FOR_TEXT,_MAPS,_IMAGES,_LISTS,_AUDIO,_VIDEO,_LINKS,_FORMS._KEY": "Yazarlara metin, haritalar, resimler, listeler, ses, video, bağlantılar, formlar için kullanmaya hazır.",
            "YOU_CAN_WRITE_YOUR_OWN_RENDERERS,_IT_IS_JUST_NORMAL_PLUGINS._KEY": "Kendi çantalarınızı yazabilirsiniz, sadece normal eklentiler.",
            "KICK_OUT_TESTS_KEY": "Kick out testleri",
            "INFOHUB_WOULD_JUST_LOVE_TO_KICK_YOU_OUT_IF_YOU_DO_NOT_BEHAVE_EXACTLY_AS_EXPECTED._KEY": "Infohub sadece tam olarak beklendiği gibi davranmadıysanız sizi vurmayı sevecektir.",
            "EVERY_CALL_YOU_MAKE_MUST_PASS_THE_QUICK_TESTS._KEY": "Yapmanız gereken her çağrı hızlı testleri geçmelidir.",
            "THERE_IS_A_BAN_SYSTEM_THAT_ALWAYS_GIVE_YOU_1_SECOND_BAN_TIME_FOR_A_VALID_CALL,_AND_MORE_FOR_AN_INVALID_CALL._KEY": "Her zaman size geçerli bir çağrı için ikinci bir yasak zamanı veren bir yasak sistemi var ve geçersiz bir çağrı için daha fazlası.",
            "AUTOMATED_TESTS_KEY": "Otomatik testler",
            "AN_INFOHUB_PLUGIN_EXPECT_AN_INCOMING_ARRAY_AND_GIVE_AN_YOU_AN_ARRAY_BACK._KEY": "Bir infohub eklenti gelen bir dizi bekler ve size bir dizi geri verir.",
            "THERE_ARE_NO_OTHER_SOURCES_OF_INPUT_OR_OUTPUT,_NO_GLOBAL_VARIABLES_ETC._KEY": "Başka bir giriş veya çıkış kaynakları yok, küresel değişkenler yok.",
            "THE_TEST_SYSTEM_ASK_THE_PLUGIN_WHAT_FUNCTIONS_IT_HAS_AND_THEN_CALL_EACH_OF_THEM_WITH_DATA_FROM_THE_TEST_FILE,_OR_AN_EMPTY_ARRAY._KEY": "Test sistemi, hangi işlevleri olduğunu ve sonra her birini test dosyasından veya boş bir diziden gelen verilerle çağırın.",
            "THE_FUNCTION_GET_THE_DEFAULT_VALUES_AND_GIVE_THE_DEFAULT_ANSWER._KEY": "İşlev varsayılan değerleri alır ve varsayılan cevabı verir.",
            "THE_ARRAYS_ARE_SAVED_IN_A_TEST_FILE_FOR_EACH_PLUGIN._KEY": "Diziler her eklenti için bir test dosyasında kaydedilir.",
            "IN_A_FUTURE_RELEASE_I_WILL_ALSO_SAVE_LIVE_DATA_TO_THE_TEST_SYSTEM._KEY": "Gelecekteki bir sürümde, test sistemine canlı verileri de kurtaracağım.",
            "THIS_MEANS_THAT_THE_TESTS_WRITE_THEM_SELF._KEY": "Bu, testlerin kendilerine yazdığı anlamına gelir.",
            "AUTOMATED_INSPECTIONS_KEY": "Otomatik denetimler",
            "THIRD_PARTY_INTERACTIONS_FROM_THE_CLIENT_IS_NOT_ALLOWED._KEY": "Müşteriden üçüncü parti etkileşimleri izin verilmez.",
            "THE_CLIENT_ONLY_SPEAK_WITH_THE_SERVER._KEY": "Müşteri sadece sunucuyla konuşur.",
            "AN_INSPECTOR_PATROL_THE_HTML_AND_GIVE_A_WARNING_FOR_ANY_EXTERNAL_LINK._KEY": "Bir denetimci html'i takip eder ve herhangi bir dış bağlantı için bir uyarı verir.",
            "MULTI_DOMAIN_KEY": "Multi domain",
            "ONE_WEBSITE_CAN_HAVE_MULTIPLE_DOMAINS_AND_SUB_DOMAINS._KEY": "Bir web sitesi birden fazla domain ve alt alana sahip olabilir.",
            "YOU_DEFINE_IN_THE_GLOBAL_CONFIGURATION_WHAT_START_MESSAGE_SHOULD_BE_SEND_FOR_EACH_DOMAIN._KEY": "Her alan için başlangıç mesajının gönderilmesi gereken küresel yapılandırmada tanımlayabilirsiniz.",
            "THERE_IS_A_DEFAULT_FALLBACK._YOU_CAN_THEN_GET_DIFFERENT_CONTENTS_FOR_EACH_DOMAIN._KEY": "Varsayılan bir düşüş var. Daha sonra her alan için farklı içerikler alabilirsiniz.",
            "MULTI_NODES_KEY": "Çok fazla düğüm",
            "THE_CLIENT_CAN_ONLY_TALK_WITH_THE_SERVER._KEY": "Müşteri sadece sunucuyla konuşabilir.",
            "THE_SERVER_CAN_TALK_WITH_OTHER_INFOHUB_SERVERS_ON_THE_INTERNET._KEY": "Sunucu internetteki diğer infohub sunucularıyla konuşabilir.",
            "EACH_PARTY_IS_CALLED_A_NODE._KEY": "Her parti bir node olarak adlandırılır.",
            "YOU_NEED_LOGIN_CREDENTIALS_TO_A_NODE_TO_EXCHANGE_MESSAGES._KEY": "Mesajları değiştirmek için giriş kimliklerine ihtiyacınız var.",
            "HISTORY_KEY": "Tarih Tarihi",
            "THE_IDEA_ABOUT_A_MESSAGE_DRIVEN_SYSTEM_CAME_TO_ME_IN_1990_WHILE_I_WAS_DESIGNING_HARDWARE._KEY": "Bir mesaj tahrik sistemi hakkındaki fikir 1990 yılında bana donanım tasarlarken geldi.",
            "WHAT_ABOUT_A_SYSTEM_WITH_INDEPENDENT_MODULES_THAT_CAN_SEND_MESSAGES_TO_EACH_OTHER._KEY": "Her birine mesaj gönderebilir bağımsız modüllerle ilgili bir sistem hakkında ne.",
            "MY_THOUGHT_WAS_THAT_WE_BY_2010_WOULD_EXPAND_OUR_COMPUTERS_WITH_PROCESSOR_MODULES,_GRAPHICS_MODULES,_STORAGE_MODULES,_POWER_MODULES,_ETC_IN_INFINITY._KEY": "Benim düşüncem, 2010 yılına kadar bilgisayarlarımızı işlemci modülleri, grafik modülleri, depolama modülleri, güç modülleri vs infinity ile genişletecektir.",
            "BY_2000_I_DESIGNED_A_CMS_SYSTEM_FOR_MY_HOME_PAGE._WRITTEN_IN_ASP_AND_ACCESS_DATABASES._KEY": "2000 yılına kadar ev sayfam için bir cm sistemi tasarladım. Asp ve erişim veritabanında yazılı.",
            "A_GREAT_LEARNING._SOME_OF_THE_IDEAS_ARE_NOW_IN_INFOHUB._KEY": "Harika bir öğrenme. Bazı fikirler şimdi Infohub'da.",
            "2010-01-01_STARTED_DEVELOPMENT_OF_INFOHUB._KEY": "2010-01-01 infohub'un gelişimine başladı.",
            "I_COULD_WORK_SOME_HOURS_LOW_QUALITY_TIME_HERE_AND_THERE_BUT_I_NEVER_GAVE_UP._KEY": "Burada birkaç saat düşük kaliteli zaman çalışabilirdim ve orada ama asla pes etmedim.",
            "BY_LATE_2011_I_BECAME_A_PROGRAMMER_BY_PROFESSION,_AND_BY_NOW_I_AM_A_PROFESSIONAL_PROGRAMMER._KEY": "2011 yılının sonlarında meslek tarafından programcı oldum ve şimdi profesyonel bir programcıyım.",
            "WE_ARE_AT_2019_AND_I_AM_PROUD_TO_PRESENT_TO_YOU_INFOHUB_CORE._KEY": "2019'dayız ve size bilgihub çekirdeği sunmaktan gurur duyuyorum."
        },
        "infohub_welcome_welcome": {
            "WELCOME_TO_YOUR_INFOHUB_KEY": "Infohub'a hoş geldiniz",
            "WE_ARE_GOING_TO_HAVE_SO_MUCH_FUN._KEY": "Çok eğleneceğiz."
        },
        "infohub_welcome_youcan": {
            "YOU_CAN,_-WITH_INFOHUB_KEY": "Yapabilirsiniz, - infohub ile",
            "CALENDAR_KEY": "Takvim",
            "WRITE_AND_FIND_DATA_IN_YOUR_CALENDAR._KEY": "Takviminizde verileri yazın ve bul.",
            "HISTORY_AND_FUTURE_IS_JUST_AS_IMPORTANT._KEY": "Tarih ve gelecek sadece önemli.",
            "DO_NOT_MISS_NAME_DAYS,_BIRTHDAYS,_ANNIVERSARIES,_HOLIDAYS,_EVENTS._YOU_CAN_SEE_TIMES_FOR_THE_SUN_AND_MOON._KEY": "İsim günlerini, doğum günleri, anniversaries, tatilleri, olayları kaçırmayın. Güneş ve ay için zaman görebilirsiniz.",
            "LINKS_TO_WIKIPEDIA_FOR_NAMES_AND_HOLIDAYS_SO_YOU_CAN_READ_MORE._KEY": "İsimler ve tatiller için wikipedia'ya bağlantılar, böylece daha fazla okuyabilirsiniz.",
            "TREE_KEY": "Tree",
            "WITH_TREE_YOU_START_WITH_YOURSELF_AND_MAKE_BUBBLES_ON_SUBJECTS_AROUND_YOU._KEY": "Ağaçla kendinizle başlayın ve etrafınızdaki konularda balonlar yapın.",
            "YOU_COULD_CREATE_A_BUBBLE_FOR_YOUR_CARS._KEY": "Arabalarınız için bir balon oluşturabilirsiniz.",
            "DURING_YOUR_LIFETIME_YOU_MIGHT_OWN_MORE_THAN_ONE_CAR_AND_CREATE_A_BUBBLE_FOR_EACH_CAR._KEY": "Yaşamınız boyunca bir arabadan daha fazlasına sahip olabilirsiniz ve her araba için bir balon oluşturabilirsiniz.",
            "PERHAPS_ATTACH_A_PHOTO_AND_FILL_WITH_ANY_DATA_YOU_LIKE._KEY": "Belki bir fotoğraf ekleyin ve istediğiniz herhangi bir verilerle doldurun.",
            "PERHAPS_YOU_WANT_A_SERVICE_BUBBLE_IN_YOUR_CAR_TO_REGISTER_ALL_SERVICE_YOU_HAVE_DONE._KEY": "Belki de yaptığınız tüm hizmeti kaydetmek için arabanızda bir servis balonu istiyorsunuz.",
            "WHEN_DID_YOU_GO_TO_THE_DENTIST?_YOU_CAN_CREATE_ANY_BUBBLE_AND_FILL_THE_BUBBLE_WITH_DATA_AND_LINK_TO_OTHER_BUBBLES._KEY": "Dişçiye ne zaman gittin? Herhangi bir balon oluşturabilir ve balonu verilerle doldurabilirsiniz ve diğer balonlara bağlantı kurabilirsiniz.",
            "YOU_CAN_CREATE_A_WEB_WITH_BUBBLES_AND_CONNECTIONS_-_YOUR_LIFE_EXPERIENCES._KEY": "Balonlar ve bağlantıları ile bir web oluşturabilirsiniz - yaşam deneyimlerinizi.",
            "BODY_KEY": "Vücut Bedeni",
            "YOU_ARE_IMPORTANT!_YOU_CAN_NOT_EXIST_WITHOUT_YOUR_BODY._KEY": "Önemlisiniz! Vücudunuz olmadan var olamazsınız.",
            "THAT_MAKES_ALSO_YOUR_BODY_IMPORTANT!_KEY": "Bu da vücudunuz önemlidir!",
            "WITH_BODY_YOU_GET_PRACTICAL_TIPS_HOW_YOU_CAN_IMPROVE_YOUR_HEALTH._KEY": "Vücutla sağlığınızı nasıl geliştirebileceğiniz pratik ipuçları elde edersiniz.",
            "YOU_CAN_TRACK_YOUR_IMPROVEMENTS._KEY": "Gelişiminizi takip edebilirsiniz.",
            "IT_IS_THE_SMALL_DECISIONS_YOU_DO_EVERY_DAY_THAT_MAKE_A_DIFFERENCE_IN_YOUR_LIFE_KEY": "Her gün yaptığınız küçük kararlar, hayatınızdaki fark yaratandır",
            "STORY_EDITOR_KEY": "Story editörü",
            "PUT_TOGETHER_AN_ARTICLE_WITH_TEXT,_IMAGES,_IMAGE_TEXTS,_LINKS,_TITLES,_INGRESS,_BULLET_LISTS,_CODE_EXAMPLES._KEY": "Metin, görüntüler, görüntü metinleri, bağlantılar, başlıklar, ingress, mermi listeleri, kod örnekleri ile birlikte bir makale koyun.",
            "YOU_CAN_THEN_EXPORT_YOUR_STORY_AND_USE_IT_OUTSIDE_OF_INFOHUB_OR_STORE_IT_IN_YOUR_TREE_KEY": "Daha sonra hikayenizi ihraç edebilir ve infohub dışında kullanabilir veya ağacınızda kullanabilirsiniz",
            "THINGS_KEY": "Şeyler",
            "REGISTER_YOUR_LARGER_THINGS:_WHAT_IT_IS,_WHEN_AND_WHERE_YOU_BOUGHT_IT,_THE_SERIAL_NUMBER,_WARRANTY_AND_SO_ON._KEY": "Daha büyük şeyleri kayıt edin: ne zaman ve nereden satın aldığınız, seri numarası, garanti ve bu yüzden.",
            "REGISTER_YOU_CARS_HERE_AND_ALL_SERVICE_YOU_HAVE_DONE_TO_THE_CARS._KEY": "Burada arabalarınızı paylaşın ve arabalara yaptığınız tüm hizmet.",
            "OR_YOUR_SNEAKERS_COLLECTION._KEY": "Ya da sinsi koleksiyonunuz.",
            "USAGE_KEY": "Kullanımı",
            "HERE_YOU_CAN_REGISTER_WHEN_YOU_USE_ONE_OF_YOUR_REGISTERED_THINGS._KEY": "İşte kayıtlı şeylerden birini kullandığınızda kayıt olabilirsiniz.",
            "IT_COULD_FOR_EXAMPLE_BE_ONE_OF_YOUR_SNEAKERS_WHILE_TRAINING._KEY": "Örneğin eğitim sırasında sinsilerden biri olabilir.",
            "PLANNING_KEY": "Planlama",
            "YOUR_PROJECTS._YOU_CAN_SET_UP_TASKS_IN_PROJECTS_HERE._KEY": "Projeleriniz. Burada projelerde görevler ayarlayabilirsiniz.",
            "DATE_WHEN_THINGS_MUST_BE_DONE_AND_WHEN_THEY_WERE_DONE._KEY": "İşler ne zaman yapılmalıdır ve ne zaman yapılır.",
            "DIARY_KEY": "Günlük Günlüğü",
            "HOW_WAS_YOUR_DAY._WRITE_THE_TEXT_VERSION_OF_YOUR_DAY_AND_USE_LINKS_TO_YOUR_DATA._KEY": "Güniniz nasıldı. Günün metin versiyonunu yazın ve verilerinize bağlantıları kullanın.",
            "MEDIA_KEY": "Media",
            "MEDIA_IS_IMAGES,VIDEO,AUDIO_-_YOUR_CATALOG_WITH_MEDIA_AND_ITS_META_DATA._KEY": "Medya görüntüler,video,audio - katalogunuz medya ve meta verileri ile.",
            "YOU_CAN_SEE_SMALL_VERSIONS_OF_YOUR_IMAGES_AND_MARK_THE_PERSONS_FACES_AND_CONNECT_THEM_TO_CONTACTS,_PLACES,_TRAVELS,_DATES._KEY": "Görüntülerinizin küçük versiyonlarını görebilir ve insanların yüzlerini işaret edebilir ve onlarla temaslara, yerlere, seyahatlere, tarihlere bağlanabilirsiniz.",
            "CONTACT_KEY": "İletişim",
            "THE_CONTACT_INFORMATION_TO_YOUR_FRIENDS._TELEPHONE_NUMBER,_EMAIL,_SKYPE,_ADDRESS,_BIRTHDAY,_SHOE_SIZE_OR_WHATEVER_YOU_LIKE_TO_REGISTER_ABOUT_YOUR_CONTACTS._KEY": "Arkadaşlarınıza iletişim bilgileri. Telefon numarası, e-posta, skype, adres, doğum günü, ayakkabı büyüklüğü veya bağlantılarınızı kaydetmek istediğiniz her şey.",
            "BUDGET_KEY": "Bütçe",
            "CALCULATE_YOUR_INCOME_AND_EXPECTED_EXPENSES_IN_THIS_PLUGIN._KEY": "Gelirinizi hesaplayın ve bu eklentide masrafları bekleyin.",
            "YOU_CAN_THEN_SEE_WHAT_IS_REASONABLE_TO_INVEST_IN._KEY": "Daha sonra yatırım yapmak için neyin makul olduğunu görebilirsiniz.",
            "EXPENSE_KEY": "Expense",
            "REGISTER_YOUR_PURCHASES_TO_KEEP_TRACK_WHERE_THE_MONEY_GOES._KEY": "Paranın nereye gittiğini takip etmek için alışverişlerinizi kayıt edin.",
            "PUT_EXPENCES_IN_GROUPS_SO_YOU_SEE_HOW_MUCH_YOUR_CAR_COST,_YOUR_HOBBY,_FOOD_ETC._KEY": "Gruplarda expences koyun, böylece arabanızın maliyetinin ne kadar olduğunu görüyorsunuz, hobiniz, yiyecekler vs.",
            "PERHAPS_YOU_CAN_CUT_COSTS_WITHOUT_CUTTING_DOWN_ON_COMFORT._KEY": "Belki de maliyetleri rahatlatmadan kesebilirsiniz.",
            "YOU_NEED_A_CLEAR_PICTURE_OF_YOUR_EXPENCES_TO_TAKE_THE_RIGHT_DECISIONS._KEY": "Doğru kararları almak için expanslarınızın net bir resmine ihtiyacınız var.",
            "REVIEW_KEY": "İnceleme",
            "WRITE_YOUR_REVIEWS_OF_FILMS,_BOOKS,_RECORDS,_TV_SERIES,_GAMES,_SUBSCRIPTIONS,_MAGAZINES._KEY": "Film, kitap, kayıtları, tv serisi, oyunlar, abonelikler, dergiler hakkındaki yorumlarınızı yazın.",
            "THEN_YOU_CAN_SEE_WHAT_MOVIES_YOU_HAVE_SEEN_AND_WHEN_YOU_SAW_THEM._KEY": "Sonra hangi filmlerin gördüğünü ve onları gördüğünüzde görebilirsiniz.",
            "PLACE_KEY": "Place",
            "YOU_CAN_REGISTER_PLACES_YOU_HAVE_VISITED_AND_GET_A_MAP_WITH_DOTS._KEY": "Ziyaret ettiğiniz yerleri kayıt olabilirsiniz ve dots ile bir harita alabilirsiniz.",
            "YOU_CAN_ALSO_LINK_A_PLACE_TO_A_STORY,_IMAGE,_TRAINING_AND_SO_ON._KEY": "Ayrıca bir hikaye, görüntü, eğitim ve benzeri bir yere bağlanabilirsiniz.",
            "EVENT_KEY": "Event",
            "REGISTER_EVENTS_YOU_WANT_TO_PARTICIPATE_IN_OR_HAVE_PARTICIPATED_IN._KEY": "Katılmak veya katılmak istediğiniz olayları kayıt edin.",
            "YOU_CAN_LINK_A_PLACE,_A_REVIEW_ETC._KEY": "Bir yer, bir inceleme vs bağlantı kurabilirsiniz."
        }
    }
}